{
    "Names": {
        "AD": "Andorra",
        "AE": "Obodo United Arab Emirates",
        "AF": "Mba Afghanistan",
        "AG": "Antigua & Barbuda",
        "AI": "Anguilla",
        "AL": "Albania",
        "AM": "Obodo Armenia",
        "AO": "Angola",
        "AQ": "Antarctica",
        "AR": "Argentina",
        "AS": "American Samoa",
        "AT": "Austria",
        "AU": "Australia",
        "AW": "Aruba",
        "AX": "Agwaetiti Aland",
        "AZ": "Obodo Azerbaijan",
        "BA": "Bosnia & Herzegovina",
        "BB": "Barbados",
        "BD": "Obodo Bangladesh",
        "BE": "Belgium",
        "BF": "Burkina Faso",
        "BG": "Bulgaria",
        "BH": "Obodo Bahrain",
        "BI": "Burundi",
        "BJ": "Binin",
        "BL": "St. Barthélemy",
        "BM": "Bemuda",
        "BN": "Brunei",
        "BO": "Bolivia",
        "BQ": "Caribbean Netherlands",
        "BR": "Mba Brazil",
        "BS": "Bahamas",
        "BT": "Obodo Bhutan",
        "BV": "Agwaetiti Bouvet",
        "BW": "Botswana",
        "BY": "Belarus",
        "BZ": "Belize",
        "CA": "Kanada",
        "CC": "Agwaetiti Cocos (Keeling)",
        "CD": "Congo - Kinshasa",
        "CF": "Central African Republik",
        "CG": "Congo",
        "CH": "Switzerland",
        "CI": "Côte d’Ivoire",
        "CK": "Agwaetiti Cook",
        "CL": "Chile",
        "CM": "Cameroon",
        "CN": "Mba China",
        "CO": "Colombia",
        "CR": "Kosta Rika",
        "CU": "Cuba",
        "CV": "Cape Verde",
        "CW": "Kurakao",
        "CX": "Agwaetiti Christmas",
        "CY": "Obodo Cyprus",
        "CZ": "Czechia",
        "DE": "Mba Germany",
        "DJ": "Djibouti",
        "DK": "Denmark",
        "DM": "Dominika",
        "DO": "Dominican Republik",
        "DZ": "Algeria",
        "EC": "Ecuador",
        "EE": "Estonia",
        "EG": "Egypt",
        "EH": "Ọdịda Anyanwụ Sahara",
        "ER": "Eritrea",
        "ES": "Spain",
        "ET": "Ethiopia",
        "FI": "Finland",
        "FJ": "Fiji",
        "FK": "Agwaetiti Falkland",
        "FM": "Micronesia",
        "FO": "Agwaetiti Faroe",
        "FR": "Mba France",
        "GA": "Gabon",
        "GB": "Mba United Kingdom",
        "GD": "Grenada",
        "GE": "Obodo Georgia",
        "GF": "Frenchi Guiana",
        "GG": "Guernsey",
        "GH": "Ghana",
        "GI": "Gibraltar",
        "GL": "Greenland",
        "GM": "Gambia",
        "GN": "Guinea",
        "GP": "Guadeloupe",
        "GQ": "Equatorial Guinea",
        "GR": "Greece",
        "GS": "South Georgia na Agwaetiti South Sandwich",
        "GT": "Guatemala",
        "GU": "Guam",
        "GW": "Guinea-Bissau",
        "GY": "Guyana",
        "HK": "Honk Kong mba nwere ndozi pụrụ iche n’obodo China",
        "HM": "Agwaetiti Heard na Agwaetiti McDonald",
        "HN": "Honduras",
        "HR": "Croatia",
        "HT": "Hati",
        "HU": "Hungary",
        "ID": "Indonesia",
        "IE": "Ireland",
        "IL": "Obodo Israel",
        "IM": "Isle of Man",
        "IN": "Mba India",
        "IO": "British Indian Ocean Territory",
        "IQ": "Obodo Iraq",
        "IR": "Obodo Iran",
        "IS": "Iceland",
        "IT": "Mba Italy",
        "JE": "Jersey",
        "JM": "Jamaika",
        "JO": "Obodo Jordan",
        "JP": "Mba Japan",
        "KE": "Kenya",
        "KG": "Obodo Kyrgyzstan",
        "KH": "Cambodia",
        "KI": "Kiribati",
        "KM": "Comorosu",
        "KN": "St. Kitts & Nevis",
        "KP": "Mba Ugwu Korea",
        "KR": "Mba South Korea",
        "KW": "Obodo Kuwait",
        "KY": "Agwaetiti Cayman",
        "KZ": "Obodo Kazakhstan",
        "LA": "Laos",
        "LB": "Obodo Lebanon",
        "LC": "St. Lucia",
        "LI": "Liechtenstein",
        "LK": "Obodo Sri Lanka",
        "LR": "Liberia",
        "LS": "Lesotho",
        "LT": "Lithuania",
        "LU": "Luxembourg",
        "LV": "Latvia",
        "LY": "Libyia",
        "MA": "Morocco",
        "MC": "Monaco",
        "MD": "Moldova",
        "ME": "Montenegro",
        "MF": "St. Martin",
        "MG": "Madagaskar",
        "MH": "Agwaetiti Marshall",
        "MK": "North Macedonia",
        "ML": "Mali",
        "MM": "Myanmar (Burma)",
        "MN": "Obodo Mongolia",
        "MO": "Obodo Macao nwere ndozi pụrụ iche na mba China",
        "MP": "Agwaetiti Northern Mariana",
        "MQ": "Martinique",
        "MR": "Mauritania",
        "MS": "Montserrat",
        "MT": "Malta",
        "MU": "Mauritius",
        "MV": "Maldivesa",
        "MW": "Malawi",
        "MX": "Mexico",
        "MY": "Malaysia",
        "MZ": "Mozambik",
        "NA": "Namibia",
        "NC": "New Caledonia",
        "NE": "Niger",
        "NF": "Agwaetiti Norfolk",
        "NG": "Naịjịrịa",
        "NI": "Nicaragua",
        "NL": "Netherlands",
        "NO": "Norway",
        "NP": "Obodo Nepal",
        "NR": "Nauru",
        "NU": "Niue",
        "NZ": "New Zealand",
        "OM": "Obodo Oman",
        "PA": "Panama",
        "PE": "Peru",
        "PF": "Frenchi Polynesia",
        "PG": "Papua New Guinea",
        "PH": "Philippines",
        "PK": "Obodo Pakistan",
        "PL": "Poland",
        "PM": "St. Pierre & Miquelon",
        "PN": "Agwaetiti Pitcairn",
        "PR": "Puerto Rico",
        "PS": "Obodo dị iche iche dị n’okpuru mba Palestine",
        "PT": "Portugal",
        "PW": "Palau",
        "PY": "Paraguay",
        "QA": "Obodo Qatar",
        "RE": "Réunion",
        "RO": "Romania",
        "RS": "Serbia",
        "RU": "Mba Russia",
        "RW": "Rwanda",
        "SA": "Obodo Saudi Arabia",
        "SB": "Agwaetiti Solomon",
        "SC": "Seychelles",
        "SD": "Sudan",
        "SE": "Sweden",
        "SG": "Singapore",
        "SH": "St. Helena",
        "SI": "Slovenia",
        "SJ": "Svalbard & Jan Mayen",
        "SK": "Slovakia",
        "SL": "Sierra Leone",
        "SM": "San Marino",
        "SN": "Senegal",
        "SO": "Somalia",
        "SR": "Suriname",
        "SS": "South Sudan",
        "ST": "São Tomé & Príncipe",
        "SV": "El Salvador",
        "SX": "Sint Maarten",
        "SY": "Obodo Syria",
        "SZ": "Eswatini",
        "TC": "Agwaetiti Turks na Caicos",
        "TD": "Chad",
        "TF": "Ụmụ ngalaba Frenchi Southern",
        "TG": "Togo",
        "TH": "Thailand",
        "TJ": "Obodo Tajikistan",
        "TK": "Tokelau",
        "TL": "Timor-Leste",
        "TM": "Obodo Turkmenistan",
        "TN": "Tunisia",
        "TO": "Tonga",
        "TR": "Obodo Turkey",
        "TT": "Trinidad & Tobago",
        "TV": "Tuvalu",
        "TW": "Obodo Taiwan",
        "TZ": "Tanzania",
        "UA": "Ukraine",
        "UG": "Uganda",
        "UM": "Obere Agwaetiti Dị Na Mpụga U.S",
        "US": "Mba United States",
        "UY": "Uruguay",
        "UZ": "Obodo Uzbekistan",
        "VA": "Vatican City",
        "VC": "St. Vincent & Grenadines",
        "VE": "Venezuela",
        "VG": "Agwaetiti British Virgin",
        "VI": "Agwaetiti Virgin nke US",
        "VN": "Vietnam",
        "VU": "Vanuatu",
        "WF": "Wallis & Futuna",
        "WS": "Samoa",
        "YE": "Obodo Yemen",
        "YT": "Mayotte",
        "ZA": "South Africa",
        "ZM": "Zambia",
        "ZW": "Zimbabwe"
    }
}
