{
    "Version": "2.1.8.9",
    "Names": {
        "Arab": "عربی",
        "Armn": "آرمینیائی",
        "Beng": "بنگالی",
        "Bopo": "بوپوموفو",
        "Brai": "بریل",
        "Cyrl": "سیریلک",
        "Deva": "دیوناگری",
        "Ethi": "ایتھوپیائی",
        "Geor": "جارجیائی",
        "Grek": "یونانی",
        "Gujr": "گجراتی",
        "Guru": "گرمکھی",
        "Hang": "ہنگول",
        "Hani": "ہان",
        "Hans": "آسان",
        "Hant": "روایتی",
        "Hebr": "عبرانی",
        "Hira": "ہیراگینا",
        "Jpan": "جاپانی",
        "Kana": "کٹاکانا",
        "Khmr": "خمیر",
        "Knda": "کنڑ",
        "Kore": "کوریائی",
        "Laoo": "لاؤ",
        "Latn": "لاطینی",
        "Mlym": "ملیالم",
        "Mong": "منگولیائی",
        "Mymr": "میانمار",
        "Orya": "اڑیہ",
        "Sinh": "سنہالا",
        "Taml": "تمل",
        "Telu": "تیلگو",
        "Thaa": "تھانا",
        "Thai": "تھائی",
        "Tibt": "تبتی",
        "Zsym": "علامات",
        "Zxxx": "غیر تحریر شدہ",
        "Zyyy": "عام",
        "Zzzz": "نامعلوم رسم الخط"
    }
}
