{
    "Version": "2.1.48.36",
    "Names": {
        "Africa\/Abidjan": "hora medie de Greenwich (Abidjan)",
        "Africa\/Accra": "hora medie de Greenwich (Accra)",
        "Africa\/Addis_Ababa": "Ethiopia (Addis Ababa)",
        "Africa\/Algiers": "hora de Europa central (Algiers)",
        "Africa\/Asmera": "Eritrea (Asmara)",
        "Africa\/Bamako": "hora medie de Greenwich (Bamako)",
        "Africa\/Bangui": "Republica African Central (Bangui)",
        "Africa\/Banjul": "hora medie de Greenwich (Banjul)",
        "Africa\/Bissau": "hora medie de Greenwich (Bissau)",
        "Africa\/Blantyre": "Malawi (Blantyre)",
        "Africa\/Brazzaville": "Congo (Brazzaville)",
        "Africa\/Bujumbura": "Burundi (Bujumbura)",
        "Africa\/Cairo": "hora de Europa oriental (Cairo)",
        "Africa\/Casablanca": "hora de Europa occidental (Casablanca)",
        "Africa\/Ceuta": "hora de Europa central (Ceuta)",
        "Africa\/Conakry": "hora medie de Greenwich (Conakry)",
        "Africa\/Dakar": "hora medie de Greenwich (Dakar)",
        "Africa\/Dar_es_Salaam": "Tanzania (Dar es Salaam)",
        "Africa\/Djibouti": "Djibouti (Djibouti)",
        "Africa\/Douala": "Camerun (Douala)",
        "Africa\/El_Aaiun": "hora de Europa occidental (El Aaiun)",
        "Africa\/Freetown": "hora medie de Greenwich (Freetown)",
        "Africa\/Gaborone": "Botswana (Gaborone)",
        "Africa\/Harare": "Zimbabwe (Harare)",
        "Africa\/Johannesburg": "Sudafrica (Johannesburg)",
        "Africa\/Juba": "Sudan del Sud (Juba)",
        "Africa\/Kampala": "Uganda (Kampala)",
        "Africa\/Khartoum": "Sudan (Khartoum)",
        "Africa\/Kigali": "Ruanda (Kigali)",
        "Africa\/Kinshasa": "Congo - Kinshasa (Kinshasa)",
        "Africa\/Lagos": "Nigeria (Lagos)",
        "Africa\/Libreville": "Gabon (Libreville)",
        "Africa\/Lome": "hora medie de Greenwich (Lome)",
        "Africa\/Luanda": "Angola (Luanda)",
        "Africa\/Lubumbashi": "Congo - Kinshasa (Lubumbashi)",
        "Africa\/Lusaka": "Zambia (Lusaka)",
        "Africa\/Malabo": "Guinea equatorial (Malabo)",
        "Africa\/Maputo": "Mozambique (Maputo)",
        "Africa\/Maseru": "Lesotho (Maseru)",
        "Africa\/Mbabane": "Swazilandia (Mbabane)",
        "Africa\/Mogadishu": "Somalia (Mogadishu)",
        "Africa\/Monrovia": "hora medie de Greenwich (Monrovia)",
        "Africa\/Nairobi": "Kenya (Nairobi)",
        "Africa\/Ndjamena": "Chad (Ndjamena)",
        "Africa\/Niamey": "Niger (Niamey)",
        "Africa\/Nouakchott": "hora medie de Greenwich (Nouakchott)",
        "Africa\/Ouagadougou": "hora medie de Greenwich (Ouagadougou)",
        "Africa\/Porto-Novo": "Benin (Porto-Novo)",
        "Africa\/Sao_Tome": "hora medie de Greenwich (Sao Tome)",
        "Africa\/Tripoli": "hora de Europa oriental (Tripoli)",
        "Africa\/Tunis": "hora de Europa central (Tunis)",
        "Africa\/Windhoek": "Namibia (Windhoek)",
        "America\/Adak": "hora de Hawaii-Aleutianas (Adak)",
        "America\/Anchorage": "hora de Alaska (Anchorage)",
        "America\/Anguilla": "hora atlantic (Anguilla)",
        "America\/Antigua": "hora atlantic (Antigua)",
        "America\/Araguaina": "Brasil (Araguaina)",
        "America\/Argentina\/La_Rioja": "Argentina (La Rioja)",
        "America\/Argentina\/Rio_Gallegos": "Argentina (Rio Gallegos)",
        "America\/Argentina\/Salta": "Argentina (Salta)",
        "America\/Argentina\/San_Juan": "Argentina (San Juan)",
        "America\/Argentina\/San_Luis": "Argentina (San Luis)",
        "America\/Argentina\/Tucuman": "Argentina (Tucuman)",
        "America\/Argentina\/Ushuaia": "Argentina (Ushuaia)",
        "America\/Aruba": "hora atlantic (Aruba)",
        "America\/Asuncion": "Paraguay (Asuncion)",
        "America\/Bahia": "Brasil (Bahia)",
        "America\/Bahia_Banderas": "hora central (Bahia de Banderas)",
        "America\/Barbados": "hora atlantic (Barbados)",
        "America\/Belem": "Brasil (Belem)",
        "America\/Belize": "hora central (Belize)",
        "America\/Blanc-Sablon": "hora atlantic (Blanc-Sablon)",
        "America\/Boa_Vista": "Brasil (Boa Vista)",
        "America\/Bogota": "Colombia (Bogota)",
        "America\/Boise": "hora del montanias (Boise)",
        "America\/Buenos_Aires": "Argentina (Buenos Aires)",
        "America\/Cambridge_Bay": "hora del montanias (Cambridge Bay)",
        "America\/Campo_Grande": "Brasil (Campo Grande)",
        "America\/Cancun": "hora del est (Cancun)",
        "America\/Caracas": "Venezuela (Caracas)",
        "America\/Catamarca": "Argentina (Catamarca)",
        "America\/Cayenne": "Guyana francese (Cayenne)",
        "America\/Cayman": "hora del est (Caiman)",
        "America\/Chicago": "hora central (Chicago)",
        "America\/Chihuahua": "hora del Pacifico mexican (Chihuahua)",
        "America\/Coral_Harbour": "hora del est (Atikokan)",
        "America\/Cordoba": "Argentina (Cordoba)",
        "America\/Costa_Rica": "hora central (Costa Rica)",
        "America\/Creston": "hora del montanias (Creston)",
        "America\/Cuiaba": "Brasil (Cuiaba)",
        "America\/Curacao": "hora atlantic (Curaçao)",
        "America\/Danmarkshavn": "hora medie de Greenwich (Danmarkshavn)",
        "America\/Dawson": "hora pacific (Dawson)",
        "America\/Dawson_Creek": "hora del montanias (Dawson Creek)",
        "America\/Denver": "hora del montanias (Denver)",
        "America\/Detroit": "hora del est (Detroit)",
        "America\/Dominica": "hora atlantic (Dominica)",
        "America\/Edmonton": "hora del montanias (Edmonton)",
        "America\/Eirunepe": "Brasil (Eirunepe)",
        "America\/El_Salvador": "hora central (El Salvador)",
        "America\/Fort_Nelson": "hora del montanias (Fort Nelson)",
        "America\/Fortaleza": "Brasil (Fortaleza)",
        "America\/Glace_Bay": "hora atlantic (Glace Bay)",
        "America\/Godthab": "hora de Groenlandia occidental (Nuuk)",
        "America\/Goose_Bay": "hora atlantic (Goose Bay)",
        "America\/Grand_Turk": "hora del est (Grand Turk)",
        "America\/Grenada": "hora atlantic (Grenada)",
        "America\/Guadeloupe": "hora atlantic (Guadeloupe)",
        "America\/Guatemala": "hora central (Guatemala)",
        "America\/Guayaquil": "Ecuador (Guayaquil)",
        "America\/Guyana": "Guyana (Guyana)",
        "America\/Halifax": "hora atlantic (Halifax)",
        "America\/Havana": "hora de Cuba (Havana)",
        "America\/Hermosillo": "hora del Pacifico mexican (Hermosillo)",
        "America\/Indiana\/Knox": "hora central (Knox, Indiana)",
        "America\/Indiana\/Marengo": "hora del est (Marengo, Indiana)",
        "America\/Indiana\/Petersburg": "hora del est (Petersburg, Indiana)",
        "America\/Indiana\/Tell_City": "hora central (Tell City, Indiana)",
        "America\/Indiana\/Vevay": "hora del est (Vevay, Indiana)",
        "America\/Indiana\/Vincennes": "hora del est (Vincennes, Indiana)",
        "America\/Indiana\/Winamac": "hora del est (Winamac, Indiana)",
        "America\/Indianapolis": "hora del est (Indianapolis)",
        "America\/Inuvik": "hora del montanias (Inuvik)",
        "America\/Iqaluit": "hora del est (Iqaluit)",
        "America\/Jamaica": "hora del est (Jamaica)",
        "America\/Jujuy": "Argentina (Jujuy)",
        "America\/Juneau": "hora de Alaska (Juneau)",
        "America\/Kentucky\/Monticello": "hora del est (Monticello, Kentucky)",
        "America\/Kralendijk": "hora atlantic (Kralendijk)",
        "America\/La_Paz": "Bolivia (La Paz)",
        "America\/Lima": "Peru (Lima)",
        "America\/Los_Angeles": "hora pacific (Los Angeles)",
        "America\/Louisville": "hora del est (Louisville)",
        "America\/Lower_Princes": "hora atlantic (Lower Prince’s Quarter)",
        "America\/Maceio": "Brasil (Maceio)",
        "America\/Managua": "hora central (Managua)",
        "America\/Manaus": "Brasil (Manaus)",
        "America\/Marigot": "hora atlantic (Marigot)",
        "America\/Martinique": "hora atlantic (Martinica)",
        "America\/Matamoros": "hora central (Matamoros)",
        "America\/Mazatlan": "hora del Pacifico mexican (Mazatlan)",
        "America\/Mendoza": "Argentina (Mendoza)",
        "America\/Menominee": "hora central (Menominee)",
        "America\/Merida": "hora central (Merida)",
        "America\/Metlakatla": "hora de Alaska (Metlakatla)",
        "America\/Mexico_City": "hora central (Citate de Mexico)",
        "America\/Miquelon": "hora de Saint-Pierre e Miquelon",
        "America\/Moncton": "hora atlantic (Moncton)",
        "America\/Monterrey": "hora central (Monterrey)",
        "America\/Montevideo": "Uruguay (Montevideo)",
        "America\/Montreal": "Canada (Montreal)",
        "America\/Montserrat": "hora atlantic (Montserrat)",
        "America\/Nassau": "hora del est (Nassau)",
        "America\/New_York": "hora del est (Nove York)",
        "America\/Nipigon": "hora del est (Nipigon)",
        "America\/Nome": "hora de Alaska (Nome)",
        "America\/Noronha": "Brasil (Noronha)",
        "America\/North_Dakota\/Beulah": "hora central (Beulah, Dakota del Nord)",
        "America\/North_Dakota\/Center": "hora central (Center, Dakota del Nord)",
        "America\/North_Dakota\/New_Salem": "hora central (New Salem, Dakota del Nord)",
        "America\/Ojinaga": "hora del montanias (Ojinaga)",
        "America\/Panama": "hora del est (Panama)",
        "America\/Pangnirtung": "hora del est (Pangnirtung)",
        "America\/Paramaribo": "Suriname (Paramaribo)",
        "America\/Phoenix": "hora del montanias (Phoenix)",
        "America\/Port-au-Prince": "hora del est (Port-au-Prince)",
        "America\/Port_of_Spain": "hora atlantic (Port of Spain)",
        "America\/Porto_Velho": "Brasil (Porto Velho)",
        "America\/Puerto_Rico": "hora atlantic (Porto Rico)",
        "America\/Punta_Arenas": "Chile (Punta Arenas)",
        "America\/Rainy_River": "hora central (Rainy River)",
        "America\/Rankin_Inlet": "hora central (Rankin Inlet)",
        "America\/Recife": "Brasil (Recife)",
        "America\/Regina": "hora central (Regina)",
        "America\/Resolute": "hora central (Resolute)",
        "America\/Rio_Branco": "Brasil (Rio Branco)",
        "America\/Santa_Isabel": "hora del nordwest de Mexico (Santa Isabel)",
        "America\/Santarem": "Brasil (Santarem)",
        "America\/Santiago": "Chile (Santiago)",
        "America\/Santo_Domingo": "hora atlantic (Santo Domingo)",
        "America\/Sao_Paulo": "Brasil (Sao Paulo)",
        "America\/Scoresbysund": "hora de Groenlandia oriental (Ittoqqortoormiit)",
        "America\/Sitka": "hora de Alaska (Sitka)",
        "America\/St_Barthelemy": "hora atlantic (Sancte Bartholomeo)",
        "America\/St_Johns": "hora de Terranova (Sancte Johannes de Terranova)",
        "America\/St_Kitts": "hora atlantic (Sancte Christophoro)",
        "America\/St_Lucia": "hora atlantic (Sancte Lucia)",
        "America\/St_Thomas": "hora atlantic (Sancte Thomas)",
        "America\/St_Vincent": "hora atlantic (Sancte Vincente)",
        "America\/Swift_Current": "hora central (Swift Current)",
        "America\/Tegucigalpa": "hora central (Tegucigalpa)",
        "America\/Thule": "hora atlantic (Thule)",
        "America\/Thunder_Bay": "hora del est (Thunder Bay)",
        "America\/Tijuana": "hora pacific (Tijuana)",
        "America\/Toronto": "hora del est (Toronto)",
        "America\/Tortola": "hora atlantic (Tortola)",
        "America\/Vancouver": "hora pacific (Vancouver)",
        "America\/Whitehorse": "hora pacific (Whitehorse)",
        "America\/Winnipeg": "hora central (Winnipeg)",
        "America\/Yakutat": "hora de Alaska (Yakutat)",
        "America\/Yellowknife": "hora del montanias (Yellowknife)",
        "Antarctica\/Casey": "Antarctica (Casey)",
        "Antarctica\/Davis": "Antarctica (Davis)",
        "Antarctica\/DumontDUrville": "Antarctica (Dumont d’Urville)",
        "Antarctica\/Macquarie": "Australia (Macquarie)",
        "Antarctica\/Mawson": "Antarctica (Mawson)",
        "Antarctica\/McMurdo": "Antarctica (McMurdo)",
        "Antarctica\/Palmer": "Antarctica (Palmer)",
        "Antarctica\/Rothera": "Antarctica (Rothera)",
        "Antarctica\/Syowa": "Antarctica (Syowa)",
        "Antarctica\/Troll": "hora medie de Greenwich (Troll)",
        "Antarctica\/Vostok": "Antarctica (Vostok)",
        "Arctic\/Longyearbyen": "hora de Europa central (Longyearbyen)",
        "Asia\/Aden": "Yemen (Aden)",
        "Asia\/Almaty": "Kazakhstan (Almaty)",
        "Asia\/Amman": "hora de Europa oriental (Amman)",
        "Asia\/Anadyr": "Russia (Anadyr)",
        "Asia\/Aqtau": "Kazakhstan (Aqtau)",
        "Asia\/Aqtobe": "Kazakhstan (Aqtobe)",
        "Asia\/Ashgabat": "Turkmenistan (Ashgabat)",
        "Asia\/Atyrau": "Kazakhstan (Atyrau)",
        "Asia\/Baghdad": "Irak (Baghdad)",
        "Asia\/Bahrain": "Bahrain (Bahrain)",
        "Asia\/Baku": "Azerbaidzhan (Baku)",
        "Asia\/Bangkok": "Thailandia (Bangkok)",
        "Asia\/Barnaul": "Russia (Barnaul)",
        "Asia\/Beirut": "hora de Europa oriental (Beirut)",
        "Asia\/Bishkek": "Kirghizistan (Bishkek)",
        "Asia\/Brunei": "Brunei (Brunei)",
        "Asia\/Calcutta": "India (Kolkata)",
        "Asia\/Chita": "hora de Yakutsk (Chita)",
        "Asia\/Choibalsan": "Mongolia (Choibalsan)",
        "Asia\/Colombo": "Sri Lanka (Colombo)",
        "Asia\/Damascus": "hora de Europa oriental (Damascus)",
        "Asia\/Dhaka": "Bangladesh (Dhaka)",
        "Asia\/Dili": "Timor del Est (Dili)",
        "Asia\/Dubai": "Emiratos Arabe Unite (Dubai)",
        "Asia\/Dushanbe": "Tadzhikistan (Dushanbe)",
        "Asia\/Famagusta": "hora de Europa oriental (Famagusta)",
        "Asia\/Gaza": "hora de Europa oriental (Gaza)",
        "Asia\/Hebron": "hora de Europa oriental (Hebron)",
        "Asia\/Hong_Kong": "Hong Kong SAR China (Hong Kong)",
        "Asia\/Hovd": "Mongolia (Hovd)",
        "Asia\/Irkutsk": "hora de Irkutsk",
        "Asia\/Jakarta": "Indonesia (Jakarta)",
        "Asia\/Jayapura": "Indonesia (Jayapura)",
        "Asia\/Jerusalem": "Israel (Jerusalem)",
        "Asia\/Kabul": "Afghanistan (Kabul)",
        "Asia\/Kamchatka": "Russia (Kamchatka)",
        "Asia\/Karachi": "Pakistan (Karachi)",
        "Asia\/Katmandu": "Nepal (Kathmandu)",
        "Asia\/Khandyga": "hora de Yakutsk (Chandyga)",
        "Asia\/Krasnoyarsk": "hora de Krasnoyarsk",
        "Asia\/Kuala_Lumpur": "Malaysia (Kuala Lumpur)",
        "Asia\/Kuching": "Malaysia (Kuching)",
        "Asia\/Kuwait": "Kuwait (Kuwait)",
        "Asia\/Macau": "Macao SAR China (Macao)",
        "Asia\/Magadan": "hora de Magadan",
        "Asia\/Makassar": "Indonesia (Makassar)",
        "Asia\/Manila": "Philippinas (Manila)",
        "Asia\/Muscat": "Oman (Muscat)",
        "Asia\/Nicosia": "hora de Europa oriental (Nicosia)",
        "Asia\/Novokuznetsk": "hora de Krasnoyarsk (Novokuznetsk)",
        "Asia\/Novosibirsk": "hora de Novosibirsk",
        "Asia\/Omsk": "hora de Omsk",
        "Asia\/Oral": "Kazakhstan (Oral)",
        "Asia\/Phnom_Penh": "Cambodgia (Phnom Penh)",
        "Asia\/Pontianak": "Indonesia (Pontianak)",
        "Asia\/Pyongyang": "Corea del Nord (Pyongyang)",
        "Asia\/Qatar": "Qatar (Qatar)",
        "Asia\/Qostanay": "Kazakhstan (Qostanay)",
        "Asia\/Qyzylorda": "Kazakhstan (Qyzylorda)",
        "Asia\/Rangoon": "Myanmar (Burma) (Yangon)",
        "Asia\/Riyadh": "Arabia Saudita (Riyadh)",
        "Asia\/Saigon": "Vietnam (Ho Chi Minh)",
        "Asia\/Sakhalin": "hora de Sachalin",
        "Asia\/Samarkand": "Uzbekistan (Samarkand)",
        "Asia\/Seoul": "Corea del Sud (Seoul)",
        "Asia\/Shanghai": "China (Shanghai)",
        "Asia\/Singapore": "Singapore (Singapore)",
        "Asia\/Srednekolymsk": "hora de Magadan (Srednekolymsk)",
        "Asia\/Taipei": "Taiwan (Taipei)",
        "Asia\/Tashkent": "Uzbekistan (Tashkent)",
        "Asia\/Tbilisi": "Georgia (Tbilisi)",
        "Asia\/Tehran": "Iran (Tehran)",
        "Asia\/Thimphu": "Bhutan (Thimphu)",
        "Asia\/Tokyo": "Japon (Tokyo)",
        "Asia\/Tomsk": "Russia (Tomsk)",
        "Asia\/Ulaanbaatar": "Mongolia (Ulaanbaatar)",
        "Asia\/Urumqi": "China (Urumqi)",
        "Asia\/Ust-Nera": "hora de Vladivostok (Ust-Nera)",
        "Asia\/Vientiane": "Laos (Vientiane)",
        "Asia\/Vladivostok": "hora de Vladivostok",
        "Asia\/Yakutsk": "hora de Yakutsk",
        "Asia\/Yekaterinburg": "hora de Ekaterinburg",
        "Asia\/Yerevan": "Armenia (Yerevan)",
        "Atlantic\/Azores": "hora del Azores",
        "Atlantic\/Bermuda": "hora atlantic (Bermuda)",
        "Atlantic\/Canary": "hora de Europa occidental (Canarias)",
        "Atlantic\/Cape_Verde": "Cape Verde (Cape Verde)",
        "Atlantic\/Faeroe": "hora de Europa occidental (Feroe)",
        "Atlantic\/Madeira": "hora de Europa occidental (Madeira)",
        "Atlantic\/Reykjavik": "hora medie de Greenwich (Reykjavik)",
        "Atlantic\/South_Georgia": "South Georgia & South Sandwich Islands (South Georgia)",
        "Atlantic\/St_Helena": "hora medie de Greenwich (St. Helena)",
        "Atlantic\/Stanley": "Falkland Islands (Stanley)",
        "Australia\/Adelaide": "Australia (Adelaide)",
        "Australia\/Brisbane": "Australia (Brisbane)",
        "Australia\/Broken_Hill": "Australia (Broken Hill)",
        "Australia\/Currie": "Australia (Currie)",
        "Australia\/Darwin": "Australia (Darwin)",
        "Australia\/Eucla": "Australia (Eucla)",
        "Australia\/Hobart": "Australia (Hobart)",
        "Australia\/Lindeman": "Australia (Lindeman)",
        "Australia\/Lord_Howe": "Australia (Lord Howe)",
        "Australia\/Melbourne": "Australia (Melbourne)",
        "Australia\/Perth": "Australia (Perth)",
        "Australia\/Sydney": "Australia (Sydney)",
        "CST6CDT": "hora central",
        "EST5EDT": "hora del est",
        "Etc\/GMT": "hora medie de Greenwich",
        "Etc\/UTC": "Universal Tempore Coordinate",
        "Europe\/Amsterdam": "hora de Europa central (Amsterdam)",
        "Europe\/Andorra": "hora de Europa central (Andorra)",
        "Europe\/Astrakhan": "hora de Moscova (Astrakhan)",
        "Europe\/Athens": "hora de Europa oriental (Athenas)",
        "Europe\/Belgrade": "hora de Europa central (Belgrado)",
        "Europe\/Berlin": "hora de Europa central (Berlin)",
        "Europe\/Bratislava": "hora de Europa central (Bratislava)",
        "Europe\/Brussels": "hora de Europa central (Bruxelles)",
        "Europe\/Bucharest": "hora de Europa oriental (Bucarest)",
        "Europe\/Budapest": "hora de Europa central (Budapest)",
        "Europe\/Busingen": "hora de Europa central (Büsingen)",
        "Europe\/Chisinau": "hora de Europa oriental (Chisinau)",
        "Europe\/Copenhagen": "hora de Europa central (Copenhagen)",
        "Europe\/Dublin": "hora medie de Greenwich (Dublin)",
        "Europe\/Gibraltar": "hora de Europa central (Gibraltar)",
        "Europe\/Guernsey": "hora medie de Greenwich (Guernsey)",
        "Europe\/Helsinki": "hora de Europa oriental (Helsinki)",
        "Europe\/Isle_of_Man": "hora medie de Greenwich (Insula de Man)",
        "Europe\/Istanbul": "Turchia (Istanbul)",
        "Europe\/Jersey": "hora medie de Greenwich (Jersey)",
        "Europe\/Kaliningrad": "hora de Europa oriental (Kaliningrad)",
        "Europe\/Kiev": "hora de Europa oriental (Kiev)",
        "Europe\/Kirov": "Russia (Kirov)",
        "Europe\/Lisbon": "hora de Europa occidental (Lisbona)",
        "Europe\/Ljubljana": "hora de Europa central (Ljubljana)",
        "Europe\/London": "hora medie de Greenwich (London)",
        "Europe\/Luxembourg": "hora de Europa central (Luxemburg)",
        "Europe\/Madrid": "hora de Europa central (Madrid)",
        "Europe\/Malta": "hora de Europa central (Malta)",
        "Europe\/Mariehamn": "hora de Europa oriental (Mariehamn)",
        "Europe\/Minsk": "hora de Moscova (Minsk)",
        "Europe\/Monaco": "hora de Europa central (Monaco)",
        "Europe\/Moscow": "hora de Moscova",
        "Europe\/Oslo": "hora de Europa central (Oslo)",
        "Europe\/Paris": "hora de Europa central (Paris)",
        "Europe\/Podgorica": "hora de Europa central (Podgorica)",
        "Europe\/Prague": "hora de Europa central (Praga)",
        "Europe\/Riga": "hora de Europa oriental (Riga)",
        "Europe\/Rome": "hora de Europa central (Roma)",
        "Europe\/Samara": "Russia (Samara)",
        "Europe\/San_Marino": "hora de Europa central (San Marino)",
        "Europe\/Sarajevo": "hora de Europa central (Sarajevo)",
        "Europe\/Saratov": "hora de Moscova (Saratov)",
        "Europe\/Simferopol": "hora de Moscova (Simferopol)",
        "Europe\/Skopje": "hora de Europa central (Skopje)",
        "Europe\/Sofia": "hora de Europa oriental (Sofia)",
        "Europe\/Stockholm": "hora de Europa central (Stockholm)",
        "Europe\/Tallinn": "hora de Europa oriental (Tallinn)",
        "Europe\/Tirane": "hora de Europa central (Tirana)",
        "Europe\/Ulyanovsk": "hora de Moscova (Ulyanovsk)",
        "Europe\/Uzhgorod": "hora de Europa oriental (Uzhgorod)",
        "Europe\/Vaduz": "hora de Europa central (Vaduz)",
        "Europe\/Vatican": "hora de Europa central (Vaticano)",
        "Europe\/Vienna": "hora de Europa central (Vienna)",
        "Europe\/Vilnius": "hora de Europa oriental (Vilnius)",
        "Europe\/Volgograd": "hora de Volgograd",
        "Europe\/Warsaw": "hora de Europa central (Varsovia)",
        "Europe\/Zagreb": "hora de Europa central (Zagreb)",
        "Europe\/Zaporozhye": "hora de Europa oriental (Zaporozhye)",
        "Europe\/Zurich": "hora de Europa central (Zurich)",
        "Indian\/Antananarivo": "Madagascar (Antananarivo)",
        "Indian\/Chagos": "Territorio oceanic britanno-indian (Chagos)",
        "Indian\/Christmas": "Insula de Natal (Christmas)",
        "Indian\/Cocos": "Cocos (Keeling) Islands (Cocos)",
        "Indian\/Comoro": "Comoros (Comoro)",
        "Indian\/Kerguelen": "Territorios meridional francese (Kerguelen)",
        "Indian\/Mahe": "Seychelles (Mahe)",
        "Indian\/Maldives": "Maldives (Maldives)",
        "Indian\/Mauritius": "Mauritius (Mauritius)",
        "Indian\/Mayotte": "Mayotte (Mayotte)",
        "Indian\/Reunion": "Réunion (Reunion)",
        "MST7MDT": "hora del montanias",
        "PST8PDT": "hora pacific",
        "Pacific\/Apia": "Samoa (Apia)",
        "Pacific\/Auckland": "Nove Zelanda (Auckland)",
        "Pacific\/Bougainville": "Papua Nove Guinea (Bougainville)",
        "Pacific\/Chatham": "Nove Zelanda (Chatham)",
        "Pacific\/Easter": "Chile (Easter)",
        "Pacific\/Efate": "Vanuatu (Efate)",
        "Pacific\/Enderbury": "Kiribati (Enderbury)",
        "Pacific\/Fakaofo": "Tokelau (Fakaofo)",
        "Pacific\/Fiji": "Fiji (Fiji)",
        "Pacific\/Funafuti": "Tuvalu (Funafuti)",
        "Pacific\/Galapagos": "Ecuador (Galapagos)",
        "Pacific\/Gambier": "Polynesia francese (Gambier)",
        "Pacific\/Guadalcanal": "Insulas Solomon (Guadalcanal)",
        "Pacific\/Guam": "Guam (Guam)",
        "Pacific\/Honolulu": "hora de Hawaii-Aleutianas (Honolulu)",
        "Pacific\/Johnston": "hora de Hawaii-Aleutianas (Johnston)",
        "Pacific\/Kiritimati": "Kiribati (Kiritimati)",
        "Pacific\/Kosrae": "Micronesia (Kosrae)",
        "Pacific\/Kwajalein": "Insulas Marshall (Kwajalein)",
        "Pacific\/Majuro": "Insulas Marshall (Majuro)",
        "Pacific\/Marquesas": "Polynesia francese (Marquesas)",
        "Pacific\/Midway": "U.S. Outlying Islands (Midway)",
        "Pacific\/Nauru": "Nauru (Nauru)",
        "Pacific\/Niue": "Niue (Niue)",
        "Pacific\/Norfolk": "Insula Norfolk (Norfolk)",
        "Pacific\/Noumea": "Nove Caledonia (Noumea)",
        "Pacific\/Pago_Pago": "Samoa american (Pago Pago)",
        "Pacific\/Palau": "Palau (Palau)",
        "Pacific\/Pitcairn": "Pitcairn Islands (Pitcairn)",
        "Pacific\/Ponape": "Micronesia (Pohnpei)",
        "Pacific\/Port_Moresby": "Papua Nove Guinea (Port Moresby)",
        "Pacific\/Rarotonga": "Insulas Cook (Rarotonga)",
        "Pacific\/Saipan": "Insulas Marianna del Nord (Saipan)",
        "Pacific\/Tahiti": "Polynesia francese (Tahiti)",
        "Pacific\/Tarawa": "Kiribati (Tarawa)",
        "Pacific\/Tongatapu": "Tonga (Tongatapu)",
        "Pacific\/Truk": "Micronesia (Chuuk)",
        "Pacific\/Wake": "U.S. Outlying Islands (Wake)",
        "Pacific\/Wallis": "Wallis & Futuna (Wallis)"
    },
    "Meta": {
        "GmtFormat": "GMT%s",
        "HourFormat": [
            "+%02d:%02d",
            "-%02d:%02d"
        ]
    }
}
