{
    "Version": "2.1.48.20",
    "Names": {
        "Africa\/Abidjan": "Greenwich Mean Time (Abidjan)",
        "Africa\/Accra": "Greenwich Mean Time (Accra)",
        "Africa\/Addis_Ababa": "Oras sa Silangang Africa (Addis Ababa)",
        "Africa\/Algiers": "Oras sa Gitnang Europe (Algiers)",
        "Africa\/Asmera": "Oras sa Silangang Africa (Asmara)",
        "Africa\/Bamako": "Greenwich Mean Time (Bamako)",
        "Africa\/Bangui": "Oras sa Kanlurang Africa (Bangui)",
        "Africa\/Banjul": "Greenwich Mean Time (Banjul)",
        "Africa\/Bissau": "Greenwich Mean Time (Bissau)",
        "Africa\/Blantyre": "Oras sa Gitnang Africa (Blantyre)",
        "Africa\/Brazzaville": "Oras sa Kanlurang Africa (Brazzaville)",
        "Africa\/Bujumbura": "Oras sa Gitnang Africa (Bujumbura)",
        "Africa\/Cairo": "Oras sa Silangang Europe (Cairo)",
        "Africa\/Casablanca": "Oras sa Kanlurang Europe (Casablanca)",
        "Africa\/Ceuta": "Oras sa Gitnang Europe (Ceuta)",
        "Africa\/Conakry": "Greenwich Mean Time (Conakry)",
        "Africa\/Dakar": "Greenwich Mean Time (Dakar)",
        "Africa\/Dar_es_Salaam": "Oras sa Silangang Africa (Dar es Salaam)",
        "Africa\/Djibouti": "Oras sa Silangang Africa (Djibouti)",
        "Africa\/Douala": "Oras sa Kanlurang Africa (Douala)",
        "Africa\/El_Aaiun": "Oras sa Kanlurang Europe (El Aaiun)",
        "Africa\/Freetown": "Greenwich Mean Time (Freetown)",
        "Africa\/Gaborone": "Oras sa Gitnang Africa (Gaborone)",
        "Africa\/Harare": "Oras sa Gitnang Africa (Harare)",
        "Africa\/Johannesburg": "Oras sa Timog Africa (Johannesburg)",
        "Africa\/Juba": "Oras sa Silangang Africa (Juba)",
        "Africa\/Kampala": "Oras sa Silangang Africa (Kampala)",
        "Africa\/Khartoum": "Oras sa Gitnang Africa (Khartoum)",
        "Africa\/Kigali": "Oras sa Gitnang Africa (Kigali)",
        "Africa\/Kinshasa": "Oras sa Kanlurang Africa (Kinshasa)",
        "Africa\/Lagos": "Oras sa Kanlurang Africa (Lagos)",
        "Africa\/Libreville": "Oras sa Kanlurang Africa (Libreville)",
        "Africa\/Lome": "Greenwich Mean Time (Lome)",
        "Africa\/Luanda": "Oras sa Kanlurang Africa (Luanda)",
        "Africa\/Lubumbashi": "Oras sa Gitnang Africa (Lubumbashi)",
        "Africa\/Lusaka": "Oras sa Gitnang Africa (Lusaka)",
        "Africa\/Malabo": "Oras sa Kanlurang Africa (Malabo)",
        "Africa\/Maputo": "Oras sa Gitnang Africa (Maputo)",
        "Africa\/Maseru": "Oras sa Timog Africa (Maseru)",
        "Africa\/Mbabane": "Oras sa Timog Africa (Mbabane)",
        "Africa\/Mogadishu": "Oras sa Silangang Africa (Mogadishu)",
        "Africa\/Monrovia": "Greenwich Mean Time (Monrovia)",
        "Africa\/Nairobi": "Oras sa Silangang Africa (Nairobi)",
        "Africa\/Ndjamena": "Oras sa Kanlurang Africa (Ndjamena)",
        "Africa\/Niamey": "Oras sa Kanlurang Africa (Niamey)",
        "Africa\/Nouakchott": "Greenwich Mean Time (Nouakchott)",
        "Africa\/Ouagadougou": "Greenwich Mean Time (Ouagadougou)",
        "Africa\/Porto-Novo": "Oras sa Kanlurang Africa (Porto-Novo)",
        "Africa\/Sao_Tome": "Greenwich Mean Time (Sao Tome)",
        "Africa\/Tripoli": "Oras sa Silangang Europe (Tripoli)",
        "Africa\/Tunis": "Oras sa Gitnang Europe (Tunis)",
        "Africa\/Windhoek": "Oras sa Gitnang Africa (Windhoek)",
        "America\/Adak": "Oras sa Hawaii-Aleutian (Adak)",
        "America\/Anchorage": "Oras sa Alaska (Anchorage)",
        "America\/Anguilla": "Oras sa Atlantiko (Anguilla)",
        "America\/Antigua": "Oras sa Atlantiko (Antigua)",
        "America\/Araguaina": "Oras sa Brasilia (Araguaina)",
        "America\/Argentina\/La_Rioja": "Oras sa Argentina (La Rioja)",
        "America\/Argentina\/Rio_Gallegos": "Oras sa Argentina (Rio Gallegos)",
        "America\/Argentina\/Salta": "Oras sa Argentina (Salta)",
        "America\/Argentina\/San_Juan": "Oras sa Argentina (San Juan)",
        "America\/Argentina\/San_Luis": "Oras sa Kanlurang Argentina (San Luis)",
        "America\/Argentina\/Tucuman": "Oras sa Argentina (Tucuman)",
        "America\/Argentina\/Ushuaia": "Oras sa Argentina (Ushuaia)",
        "America\/Aruba": "Oras sa Atlantiko (Aruba)",
        "America\/Asuncion": "Oras sa Paraguay (Asunción)",
        "America\/Bahia": "Oras sa Brasilia (Bahia)",
        "America\/Bahia_Banderas": "Sentral na Oras (Bahia Banderas)",
        "America\/Barbados": "Oras sa Atlantiko (Barbados)",
        "America\/Belem": "Oras sa Brasilia (Belem)",
        "America\/Belize": "Sentral na Oras (Belize)",
        "America\/Blanc-Sablon": "Oras sa Atlantiko (Blanc-Sablon)",
        "America\/Boa_Vista": "Oras sa Amazon (Boa Vista)",
        "America\/Bogota": "Oras sa Colombia (Bogota)",
        "America\/Boise": "Oras sa Bundok (Boise)",
        "America\/Buenos_Aires": "Oras sa Argentina (Buenos Aires)",
        "America\/Cambridge_Bay": "Oras sa Bundok (Cambridge Bay)",
        "America\/Campo_Grande": "Oras sa Amazon (Campo Grande)",
        "America\/Cancun": "Eastern Time (Cancun)",
        "America\/Caracas": "Oras sa Venezuela (Caracas)",
        "America\/Catamarca": "Oras sa Argentina (Catamarca)",
        "America\/Cayenne": "Oras sa French Guiana (Cayenne)",
        "America\/Cayman": "Eastern Time (Cayman)",
        "America\/Chicago": "Sentral na Oras (Chicago)",
        "America\/Chihuahua": "Oras sa Pasipiko ng Mexico (Chihuahua)",
        "America\/Coral_Harbour": "Eastern Time (Atikokan)",
        "America\/Cordoba": "Oras sa Argentina (Cordoba)",
        "America\/Costa_Rica": "Sentral na Oras (Costa Rica)",
        "America\/Creston": "Oras sa Bundok (Creston)",
        "America\/Cuiaba": "Oras sa Amazon (Cuiaba)",
        "America\/Curacao": "Oras sa Atlantiko (Curacao)",
        "America\/Danmarkshavn": "Greenwich Mean Time (Danmarkshavn)",
        "America\/Dawson": "Oras sa Pasipiko (Dawson)",
        "America\/Dawson_Creek": "Oras sa Bundok (Dawson Creek)",
        "America\/Denver": "Oras sa Bundok (Denver)",
        "America\/Detroit": "Eastern Time (Detroit)",
        "America\/Dominica": "Oras sa Atlantiko (Dominica)",
        "America\/Edmonton": "Oras sa Bundok (Edmonton)",
        "America\/El_Salvador": "Sentral na Oras (El Salvador)",
        "America\/Fort_Nelson": "Oras sa Bundok (Fort Nelson)",
        "America\/Fortaleza": "Oras sa Brasilia (Fortaleza)",
        "America\/Glace_Bay": "Oras sa Atlantiko (Glace Bay)",
        "America\/Godthab": "Oras sa Kanlurang Greenland (Nuuk)",
        "America\/Goose_Bay": "Oras sa Atlantiko (Goose Bay)",
        "America\/Grand_Turk": "Eastern Time (Grand Turk)",
        "America\/Grenada": "Oras sa Atlantiko (Grenada)",
        "America\/Guadeloupe": "Oras sa Atlantiko (Guadeloupe)",
        "America\/Guatemala": "Sentral na Oras (Guatemala)",
        "America\/Guayaquil": "Oras sa Ecuador (Guayaquil)",
        "America\/Guyana": "Oras sa Guyana (Guyana)",
        "America\/Halifax": "Oras sa Atlantiko (Halifax)",
        "America\/Havana": "Oras sa Cuba (Havana)",
        "America\/Hermosillo": "Oras sa Pasipiko ng Mexico (Hermosillo)",
        "America\/Indiana\/Knox": "Sentral na Oras (Knox, Indiana)",
        "America\/Indiana\/Marengo": "Eastern Time (Marengo, Indiana)",
        "America\/Indiana\/Petersburg": "Eastern Time (Petersburg, Indiana)",
        "America\/Indiana\/Tell_City": "Sentral na Oras (Tell City, Indiana)",
        "America\/Indiana\/Vevay": "Eastern Time (Vevay, Indiana)",
        "America\/Indiana\/Vincennes": "Eastern Time (Vincennes, Indiana)",
        "America\/Indiana\/Winamac": "Eastern Time (Winamac, Indiana)",
        "America\/Indianapolis": "Eastern Time (Indianapolis)",
        "America\/Inuvik": "Oras sa Bundok (Inuvik)",
        "America\/Iqaluit": "Eastern Time (Iqaluit)",
        "America\/Jamaica": "Eastern Time (Jamaica)",
        "America\/Jujuy": "Oras sa Argentina (Jujuy)",
        "America\/Juneau": "Oras sa Alaska (Juneau)",
        "America\/Kentucky\/Monticello": "Eastern Time (Monticello, Kentucky)",
        "America\/Kralendijk": "Oras sa Atlantiko (Kralendijk)",
        "America\/La_Paz": "Oras sa Bolivia (La Paz)",
        "America\/Lima": "Oras sa Peru (Lima)",
        "America\/Los_Angeles": "Oras sa Pasipiko (Los Angeles)",
        "America\/Louisville": "Eastern Time (Louisville)",
        "America\/Lower_Princes": "Oras sa Atlantiko (Lower Prince’s Quarter)",
        "America\/Maceio": "Oras sa Brasilia (Maceio)",
        "America\/Managua": "Sentral na Oras (Managua)",
        "America\/Manaus": "Oras sa Amazon (Manaus)",
        "America\/Marigot": "Oras sa Atlantiko (Marigot)",
        "America\/Martinique": "Oras sa Atlantiko (Martinique)",
        "America\/Matamoros": "Sentral na Oras (Matamoros)",
        "America\/Mazatlan": "Oras sa Pasipiko ng Mexico (Mazatlan)",
        "America\/Mendoza": "Oras sa Argentina (Mendoza)",
        "America\/Menominee": "Sentral na Oras (Menominee)",
        "America\/Merida": "Sentral na Oras (Merida)",
        "America\/Metlakatla": "Oras sa Alaska (Metlakatla)",
        "America\/Mexico_City": "Sentral na Oras (Lungsod ng Mexico)",
        "America\/Miquelon": "Oras sa Saint Pierre & Miquelon (Miquelon)",
        "America\/Moncton": "Oras sa Atlantiko (Moncton)",
        "America\/Monterrey": "Sentral na Oras (Monterrey)",
        "America\/Montevideo": "Oras sa Uruguay (Montevideo)",
        "America\/Montserrat": "Oras sa Atlantiko (Montserrat)",
        "America\/Nassau": "Eastern Time (Nassau)",
        "America\/New_York": "Eastern Time (New York)",
        "America\/Nipigon": "Eastern Time (Nipigon)",
        "America\/Nome": "Oras sa Alaska (Nome)",
        "America\/Noronha": "Oras sa Fernando de Noronha (Noronha)",
        "America\/North_Dakota\/Beulah": "Sentral na Oras (Beulah, North Dakota)",
        "America\/North_Dakota\/Center": "Sentral na Oras (Center, North Dakota)",
        "America\/North_Dakota\/New_Salem": "Sentral na Oras (New Salem, North Dakota)",
        "America\/Ojinaga": "Oras sa Bundok (Ojinaga)",
        "America\/Panama": "Eastern Time (Panama)",
        "America\/Pangnirtung": "Eastern Time (Pangnirtung)",
        "America\/Paramaribo": "Oras sa Suriname (Paramaribo)",
        "America\/Phoenix": "Oras sa Bundok (Phoenix)",
        "America\/Port-au-Prince": "Eastern Time (Port-au-Prince)",
        "America\/Port_of_Spain": "Oras sa Atlantiko (Puwerto ng Espanya)",
        "America\/Porto_Velho": "Oras sa Amazon (Porto Velho)",
        "America\/Puerto_Rico": "Oras sa Atlantiko (Puerto Rico)",
        "America\/Punta_Arenas": "Oras sa Chile (Punta Arenas)",
        "America\/Rainy_River": "Sentral na Oras (Rainy River)",
        "America\/Rankin_Inlet": "Sentral na Oras (Makipot na Look ng Rankin)",
        "America\/Recife": "Oras sa Brasilia (Recife)",
        "America\/Regina": "Sentral na Oras (Regina)",
        "America\/Resolute": "Sentral na Oras (Resolute)",
        "America\/Santa_Isabel": "Oras sa Hilagang-kanlurang Mexico (Santa Isabel)",
        "America\/Santarem": "Oras sa Brasilia (Santarem)",
        "America\/Santiago": "Oras sa Chile (Santiago)",
        "America\/Santo_Domingo": "Oras sa Atlantiko (Santo Domingo)",
        "America\/Sao_Paulo": "Oras sa Brasilia (Sao Paulo)",
        "America\/Scoresbysund": "Oras sa Silangang Greenland (Ittoqqortoormiit)",
        "America\/Sitka": "Oras sa Alaska (Sitka)",
        "America\/St_Barthelemy": "Oras sa Atlantiko (St. Barthélemy)",
        "America\/St_Johns": "Oras sa Newfoundland (St. John’s)",
        "America\/St_Kitts": "Oras sa Atlantiko (St. Kitts)",
        "America\/St_Lucia": "Oras sa Atlantiko (St. Lucia)",
        "America\/St_Thomas": "Oras sa Atlantiko (St. Thomas)",
        "America\/St_Vincent": "Oras sa Atlantiko (St. Vincent)",
        "America\/Swift_Current": "Sentral na Oras (Swift Current)",
        "America\/Tegucigalpa": "Sentral na Oras (Tegucigalpa)",
        "America\/Thule": "Oras sa Atlantiko (Thule)",
        "America\/Thunder_Bay": "Eastern Time (Thunder Bay)",
        "America\/Tijuana": "Oras sa Pasipiko (Tijuana)",
        "America\/Toronto": "Eastern Time (Toronto)",
        "America\/Tortola": "Oras sa Atlantiko (Tortola)",
        "America\/Vancouver": "Oras sa Pasipiko (Vancouver)",
        "America\/Whitehorse": "Oras sa Pasipiko (Whitehorse)",
        "America\/Winnipeg": "Sentral na Oras (Winnipeg)",
        "America\/Yakutat": "Oras sa Alaska (Yakutat)",
        "America\/Yellowknife": "Oras sa Bundok (Yellowknife)",
        "Antarctica\/Casey": "Oras sa Kanlurang Australya (Casey)",
        "Antarctica\/Davis": "Oras sa Davis (Davis)",
        "Antarctica\/DumontDUrville": "Oras sa Dumont-d’Urville (Dumont d’Urville)",
        "Antarctica\/Macquarie": "Oras sa Macquarie Island (Macquarie)",
        "Antarctica\/Mawson": "Oras sa Mawson (Mawson)",
        "Antarctica\/McMurdo": "Oras sa New Zealand (McMurdo)",
        "Antarctica\/Palmer": "Oras sa Chile (Palmer)",
        "Antarctica\/Rothera": "Oras sa Rothera (Rothera)",
        "Antarctica\/Syowa": "Oras sa Syowa (Syowa)",
        "Antarctica\/Troll": "Greenwich Mean Time (Troll)",
        "Antarctica\/Vostok": "Oras sa Vostok (Vostok)",
        "Arctic\/Longyearbyen": "Oras sa Gitnang Europe (Longyearbyen)",
        "Asia\/Aden": "Oras sa Arabia (Aden)",
        "Asia\/Almaty": "Oras sa Silangang Kazakhstan (Almaty)",
        "Asia\/Amman": "Oras sa Silangang Europe (Amman)",
        "Asia\/Anadyr": "Oras sa Anadyr (Anadyr)",
        "Asia\/Aqtau": "Oras sa Kanlurang Kazakhstan (Aqtau)",
        "Asia\/Aqtobe": "Oras sa Kanlurang Kazakhstan (Aqtobe)",
        "Asia\/Ashgabat": "Oras sa Turkmenistan (Ashgabat)",
        "Asia\/Atyrau": "Oras sa Kanlurang Kazakhstan (Atyrau)",
        "Asia\/Baghdad": "Oras sa Arabia (Baghdad)",
        "Asia\/Bahrain": "Oras sa Arabia (Bahrain)",
        "Asia\/Baku": "Oras sa Azerbaijan (Baku)",
        "Asia\/Bangkok": "Oras sa Indochina (Bangkok)",
        "Asia\/Beirut": "Oras sa Silangang Europe (Beirut)",
        "Asia\/Bishkek": "Oras sa Kyrgystan (Bishkek)",
        "Asia\/Brunei": "Oras sa Brunei Darussalam (Brunei)",
        "Asia\/Calcutta": "Standard na Oras sa Bhutan (Kolkata)",
        "Asia\/Chita": "Oras sa Yakutsk (Chita)",
        "Asia\/Choibalsan": "Oras sa Choibalsan (Choibalsan)",
        "Asia\/Colombo": "Standard na Oras sa Bhutan (Colombo)",
        "Asia\/Damascus": "Oras sa Silangang Europe (Damascus)",
        "Asia\/Dhaka": "Oras sa Bangladesh (Dhaka)",
        "Asia\/Dili": "Oras sa East Timor (Dili)",
        "Asia\/Dubai": "Oras sa Gulf (Dubai)",
        "Asia\/Dushanbe": "Oras sa Tajikistan (Dushanbe)",
        "Asia\/Famagusta": "Oras sa Silangang Europe (Famagusta)",
        "Asia\/Gaza": "Oras sa Silangang Europe (Gaza)",
        "Asia\/Hebron": "Oras sa Silangang Europe (Hebron)",
        "Asia\/Hong_Kong": "Oras sa Hong Kong (Hong Kong)",
        "Asia\/Hovd": "Oras sa Hovd (Hovd)",
        "Asia\/Irkutsk": "Oras sa Irkutsk (Irkutsk)",
        "Asia\/Jakarta": "Oras sa Kanlurang Indonesia (Jakarta)",
        "Asia\/Jayapura": "Oras sa Silangang Indonesia (Jayapura)",
        "Asia\/Jerusalem": "Oras sa Israel (Jerusalem)",
        "Asia\/Kabul": "Oras sa Afghanistan (Kabul)",
        "Asia\/Kamchatka": "Oras sa Petropavlovsk-Kamchatski (Kamchatka)",
        "Asia\/Karachi": "Oras sa Pakistan (Karachi)",
        "Asia\/Katmandu": "Oras sa Nepal (Kathmandu)",
        "Asia\/Khandyga": "Oras sa Yakutsk (Khandyga)",
        "Asia\/Krasnoyarsk": "Oras sa Krasnoyarsk (Krasnoyarsk)",
        "Asia\/Kuala_Lumpur": "Oras sa Malaysia (Kuala Lumpur)",
        "Asia\/Kuching": "Oras sa Malaysia (Kuching)",
        "Asia\/Kuwait": "Oras sa Arabia (Kuwait)",
        "Asia\/Macau": "Oras sa China (Macau)",
        "Asia\/Magadan": "Oras sa Magadan (Magadan)",
        "Asia\/Makassar": "Oras sa Gitnang Indonesia (Makassar)",
        "Asia\/Manila": "Oras sa Pilipinas (Manila)",
        "Asia\/Muscat": "Oras sa Gulf (Muscat)",
        "Asia\/Nicosia": "Oras sa Silangang Europe (Nicosia)",
        "Asia\/Novokuznetsk": "Oras sa Krasnoyarsk (Novokuznetsk)",
        "Asia\/Novosibirsk": "Oras sa Novosibirsk (Novosibirsk)",
        "Asia\/Omsk": "Oras sa Omsk (Omsk)",
        "Asia\/Oral": "Oras sa Kanlurang Kazakhstan (Oral)",
        "Asia\/Phnom_Penh": "Oras sa Indochina (Phnom Penh)",
        "Asia\/Pontianak": "Oras sa Kanlurang Indonesia (Pontianak)",
        "Asia\/Pyongyang": "Oras sa Korea (Pyongyang)",
        "Asia\/Qatar": "Oras sa Arabia (Qatar)",
        "Asia\/Qostanay": "Oras sa Silangang Kazakhstan (Kostanay)",
        "Asia\/Qyzylorda": "Oras sa Kanlurang Kazakhstan (Qyzylorda)",
        "Asia\/Rangoon": "Oras sa Myanmar (Rangoon)",
        "Asia\/Riyadh": "Oras sa Arabia (Riyadh)",
        "Asia\/Saigon": "Oras sa Indochina (Lungsod ng Ho Chi Minh)",
        "Asia\/Sakhalin": "Oras sa Sakhalin (Sakhalin)",
        "Asia\/Samarkand": "Oras sa Uzbekistan (Samarkand)",
        "Asia\/Seoul": "Oras sa Korea (Seoul)",
        "Asia\/Shanghai": "Oras sa China (Shanghai)",
        "Asia\/Singapore": "Standard na Oras sa Singapore (Singapore)",
        "Asia\/Srednekolymsk": "Oras sa Magadan (Srednekolymsk)",
        "Asia\/Taipei": "Oras sa Taipei (Taipei)",
        "Asia\/Tashkent": "Oras sa Uzbekistan (Tashkent)",
        "Asia\/Tbilisi": "Oras sa Georgia (Tbilisi)",
        "Asia\/Tehran": "Oras sa Iran (Tehran)",
        "Asia\/Thimphu": "Oras sa Bhutan (Thimphu)",
        "Asia\/Tokyo": "Oras sa Japan (Tokyo)",
        "Asia\/Ulaanbaatar": "Oras sa Ulan Bator (Ulaanbaatar)",
        "Asia\/Ust-Nera": "Oras sa Vladivostok (Ust-Nera)",
        "Asia\/Vientiane": "Oras sa Indochina (Vientiane)",
        "Asia\/Vladivostok": "Oras sa Vladivostok (Vladivostok)",
        "Asia\/Yakutsk": "Oras sa Yakutsk (Yakutsk)",
        "Asia\/Yekaterinburg": "Oras sa Yekaterinburg (Yekaterinburg)",
        "Asia\/Yerevan": "Oras sa Armenia (Yerevan)",
        "Atlantic\/Azores": "Oras sa Azores (Azores)",
        "Atlantic\/Bermuda": "Oras sa Atlantiko (Bermuda)",
        "Atlantic\/Canary": "Oras sa Kanlurang Europe (Canary)",
        "Atlantic\/Cape_Verde": "Oras sa Cape Verde (Cape Verde)",
        "Atlantic\/Faeroe": "Oras sa Kanlurang Europe (Faroe)",
        "Atlantic\/Madeira": "Oras sa Kanlurang Europe (Madeira)",
        "Atlantic\/Reykjavik": "Greenwich Mean Time (Reykjavik)",
        "Atlantic\/South_Georgia": "Oras sa Timog Georgia (South Georgia)",
        "Atlantic\/St_Helena": "Greenwich Mean Time (St. Helena)",
        "Atlantic\/Stanley": "Oras sa Falkland Islands (Stanley)",
        "Australia\/Adelaide": "Oras sa Gitnang Australya (Adelaide)",
        "Australia\/Brisbane": "Oras sa Silangang Australya (Brisbane)",
        "Australia\/Broken_Hill": "Oras sa Gitnang Australya (Broken Hill)",
        "Australia\/Currie": "Oras sa Silangang Australya (Currie)",
        "Australia\/Darwin": "Oras sa Gitnang Australya (Darwin)",
        "Australia\/Eucla": "Oras ng Gitnang Kanluran ng Australya (Eucla)",
        "Australia\/Hobart": "Oras sa Silangang Australya (Hobart)",
        "Australia\/Lindeman": "Oras sa Silangang Australya (Lindeman)",
        "Australia\/Lord_Howe": "Oras sa Lord Howe (Lord Howe)",
        "Australia\/Melbourne": "Oras sa Silangang Australya (Melbourne)",
        "Australia\/Perth": "Oras sa Kanlurang Australya (Perth)",
        "Australia\/Sydney": "Oras sa Silangang Australya (Sydney)",
        "CST6CDT": "Sentral na Oras",
        "EST5EDT": "Eastern Time",
        "Etc\/GMT": "Greenwich Mean Time",
        "Etc\/UTC": "Coordinated Universal Time",
        "Europe\/Amsterdam": "Oras sa Gitnang Europe (Amsterdam)",
        "Europe\/Andorra": "Oras sa Gitnang Europe (Andorra)",
        "Europe\/Astrakhan": "Oras sa Moscow (Astrakhan)",
        "Europe\/Athens": "Oras sa Silangang Europe (Athens)",
        "Europe\/Belgrade": "Oras sa Gitnang Europe (Belgrade)",
        "Europe\/Berlin": "Oras sa Gitnang Europe (Berlin)",
        "Europe\/Bratislava": "Oras sa Gitnang Europe (Bratislava)",
        "Europe\/Brussels": "Oras sa Gitnang Europe (Brussels)",
        "Europe\/Bucharest": "Oras sa Silangang Europe (Bucharest)",
        "Europe\/Budapest": "Oras sa Gitnang Europe (Budapest)",
        "Europe\/Busingen": "Oras sa Gitnang Europe (Busingen)",
        "Europe\/Chisinau": "Oras sa Silangang Europe (Chisinau)",
        "Europe\/Copenhagen": "Oras sa Gitnang Europe (Copenhagen)",
        "Europe\/Dublin": "Greenwich Mean Time (Dublin)",
        "Europe\/Gibraltar": "Oras sa Gitnang Europe (Gibraltar)",
        "Europe\/Guernsey": "Greenwich Mean Time (Guernsey)",
        "Europe\/Helsinki": "Oras sa Silangang Europe (Helsinki)",
        "Europe\/Isle_of_Man": "Greenwich Mean Time (Isle of Man)",
        "Europe\/Jersey": "Greenwich Mean Time (Jersey)",
        "Europe\/Kaliningrad": "Oras sa Silangang Europe (Kaliningrad)",
        "Europe\/Kiev": "Oras sa Silangang Europe (Kiev)",
        "Europe\/Lisbon": "Oras sa Kanlurang Europe (Lisbon)",
        "Europe\/Ljubljana": "Oras sa Gitnang Europe (Ljubljana)",
        "Europe\/London": "Greenwich Mean Time (London)",
        "Europe\/Luxembourg": "Oras sa Gitnang Europe (Luxembourg)",
        "Europe\/Madrid": "Oras sa Gitnang Europe (Madrid)",
        "Europe\/Malta": "Oras sa Gitnang Europe (Malta)",
        "Europe\/Mariehamn": "Oras sa Silangang Europe (Mariehamn)",
        "Europe\/Minsk": "Oras sa Moscow (Minsk)",
        "Europe\/Monaco": "Oras sa Gitnang Europe (Monaco)",
        "Europe\/Moscow": "Oras sa Moscow (Moscow)",
        "Europe\/Oslo": "Oras sa Gitnang Europe (Oslo)",
        "Europe\/Paris": "Oras sa Gitnang Europe (Paris)",
        "Europe\/Podgorica": "Oras sa Gitnang Europe (Podgorica)",
        "Europe\/Prague": "Oras sa Gitnang Europe (Prague)",
        "Europe\/Riga": "Oras sa Silangang Europe (Riga)",
        "Europe\/Rome": "Oras sa Gitnang Europe (Rome)",
        "Europe\/Samara": "Oras sa Samara (Samara)",
        "Europe\/San_Marino": "Oras sa Gitnang Europe (San Marino)",
        "Europe\/Sarajevo": "Oras sa Gitnang Europe (Sarajevo)",
        "Europe\/Saratov": "Oras sa Moscow (Saratov)",
        "Europe\/Simferopol": "Oras sa Moscow (Simferopol)",
        "Europe\/Skopje": "Oras sa Gitnang Europe (Skopje)",
        "Europe\/Sofia": "Oras sa Silangang Europe (Sofia)",
        "Europe\/Stockholm": "Oras sa Gitnang Europe (Stockholm)",
        "Europe\/Tallinn": "Oras sa Silangang Europe (Tallinn)",
        "Europe\/Tirane": "Oras sa Gitnang Europe (Tirane)",
        "Europe\/Ulyanovsk": "Oras sa Moscow (Ulyanovsk)",
        "Europe\/Uzhgorod": "Oras sa Silangang Europe (Uzhgorod)",
        "Europe\/Vaduz": "Oras sa Gitnang Europe (Vaduz)",
        "Europe\/Vatican": "Oras sa Gitnang Europe (Vatican)",
        "Europe\/Vienna": "Oras sa Gitnang Europe (Vienna)",
        "Europe\/Vilnius": "Oras sa Silangang Europe (Vilnius)",
        "Europe\/Volgograd": "Oras sa Volgograd (Volgograd)",
        "Europe\/Warsaw": "Oras sa Gitnang Europe (Warsaw)",
        "Europe\/Zagreb": "Oras sa Gitnang Europe (Zagreb)",
        "Europe\/Zaporozhye": "Oras sa Silangang Europe (Zaporozhye)",
        "Europe\/Zurich": "Oras sa Gitnang Europe (Zurich)",
        "Indian\/Antananarivo": "Oras sa Silangang Africa (Antananarivo)",
        "Indian\/Chagos": "Oras sa Indian Ocean (Chagos)",
        "Indian\/Christmas": "Oras sa Christmas Island (Christmas)",
        "Indian\/Cocos": "Oras sa Cocos Islands (Cocos)",
        "Indian\/Comoro": "Oras sa Silangang Africa (Comoro)",
        "Indian\/Kerguelen": "Oras sa Katimugang France at Antartiko (Kerguelen)",
        "Indian\/Mahe": "Oras sa Seychelles (Mahe)",
        "Indian\/Maldives": "Oras sa Maldives (Maldives)",
        "Indian\/Mauritius": "Oras sa Mauritius (Mauritius)",
        "Indian\/Mayotte": "Oras sa Silangang Africa (Mayotte)",
        "Indian\/Reunion": "Oras sa Reunion (Réunion)",
        "MST7MDT": "Oras sa Bundok",
        "PST8PDT": "Oras sa Pasipiko",
        "Pacific\/Apia": "Oras sa Apia (Apia)",
        "Pacific\/Auckland": "Oras sa New Zealand (Auckland)",
        "Pacific\/Bougainville": "Oras sa Papua New Guinea (Bougainville)",
        "Pacific\/Chatham": "Oras sa Chatham (Chatham)",
        "Pacific\/Easter": "Oras sa Easter Island (Easter)",
        "Pacific\/Efate": "Oras sa Vanuatu (Efate)",
        "Pacific\/Enderbury": "Oras sa Phoenix Islands (Enderbury)",
        "Pacific\/Fakaofo": "Oras sa Tokelau (Fakaofo)",
        "Pacific\/Fiji": "Oras sa Fiji (Fiji)",
        "Pacific\/Funafuti": "Oras sa Tuvalu (Funafuti)",
        "Pacific\/Galapagos": "Oras sa Galapagos (Galapagos)",
        "Pacific\/Gambier": "Oras sa Gambier (Gambier)",
        "Pacific\/Guadalcanal": "Oras sa Solomon Islands (Guadalcanal)",
        "Pacific\/Guam": "Standard na Oras sa Chamorro (Guam)",
        "Pacific\/Honolulu": "Oras sa Hawaii-Aleutian (Honolulu)",
        "Pacific\/Johnston": "Oras sa Hawaii-Aleutian (Johnston)",
        "Pacific\/Kiritimati": "Oras sa Line Islands (Kiritimati)",
        "Pacific\/Kosrae": "Oras sa Kosrae (Kosrae)",
        "Pacific\/Kwajalein": "Oras sa Marshall Islands (Kwajalein)",
        "Pacific\/Majuro": "Oras sa Marshall Islands (Majuro)",
        "Pacific\/Marquesas": "Oras sa Marquesas (Marquesas)",
        "Pacific\/Midway": "Oras sa Samoa (Midway)",
        "Pacific\/Nauru": "Oras sa Nauru (Nauru)",
        "Pacific\/Niue": "Oras sa Niue (Niue)",
        "Pacific\/Norfolk": "Oras sa Norfolk Island (Norfolk)",
        "Pacific\/Noumea": "Oras sa New Caledonia (Noumea)",
        "Pacific\/Pago_Pago": "Oras sa Samoa (Pago Pago)",
        "Pacific\/Palau": "Oras sa Palau (Palau)",
        "Pacific\/Pitcairn": "Oras sa Pitcairn (Pitcairn)",
        "Pacific\/Ponape": "Oras sa Ponape (Pohnpei)",
        "Pacific\/Port_Moresby": "Oras sa Papua New Guinea (Port Moresby)",
        "Pacific\/Rarotonga": "Oras sa Cook Islands (Rarotonga)",
        "Pacific\/Saipan": "Standard na Oras sa Chamorro (Saipan)",
        "Pacific\/Tahiti": "Oras sa Tahiti (Tahiti)",
        "Pacific\/Tarawa": "Oras sa Gilbert Islands (Tarawa)",
        "Pacific\/Tongatapu": "Oras sa Tonga (Tongatapu)",
        "Pacific\/Truk": "Oras sa Chuuk (Chuuk)",
        "Pacific\/Wake": "Oras sa Wake Island (Wake)",
        "Pacific\/Wallis": "Oras sa Wallis & Futuna (Wallis)"
    }
}
